Layer_Data_Replace/Data_Replace_script.py
Layer_Data_Replace/__init__.py
Layer_Data_Replace/_version.py
Layer_Data_Replace-0.0.5.dist-info/LICENSE
Layer_Data_Replace-0.0.5.dist-info/METADATA
Layer_Data_Replace-0.0.5.dist-info/WHEEL
Layer_Data_Replace-0.0.5.dist-info/entry_points.txt
Layer_Data_Replace-0.0.5.dist-info/top_level.txt
Layer_Data_Replace-0.0.5.dist-info/RECORD
